streamlit_elements/__init__.py
streamlit_elements/version.py
streamlit_elements/core/__init__.py
streamlit_elements/core/callback.py
streamlit_elements/core/element.py
streamlit_elements/core/exceptions.py
streamlit_elements/core/frame.py
streamlit_elements/core/render.py
streamlit_elements/frontend/build/404.html
streamlit_elements/frontend/build/bootstrap.min.css
streamlit_elements/frontend/build/index.html
streamlit_elements/frontend/build/_next/static/HnJ69V7KJqUEW8EWXrd50/_buildManifest.js
streamlit_elements/frontend/build/_next/static/HnJ69V7KJqUEW8EWXrd50/_ssgManifest.js
streamlit_elements/frontend/build/_next/static/chunks/1023.c5c9e5c5cb330f61.js
streamlit_elements/frontend/build/_next/static/chunks/103.73a58ebc9bc04fdb.js
streamlit_elements/frontend/build/_next/static/chunks/1034.e0a5fa6e49fe02dd.js
streamlit_elements/frontend/build/_next/static/chunks/1041.702832db88f1212e.js
streamlit_elements/frontend/build/_next/static/chunks/1060.b59fa5e89308a3a2.js
streamlit_elements/frontend/build/_next/static/chunks/1109.0a2846b2fa71fffa.js
streamlit_elements/frontend/build/_next/static/chunks/1146.8361d71abb9cec97.js
streamlit_elements/frontend/build/_next/static/chunks/1157.e48cac3e661a8dcb.js
streamlit_elements/frontend/build/_next/static/chunks/1261.2c086ee666b4c193.js
streamlit_elements/frontend/build/_next/static/chunks/1397.5e6133806543712d.js
streamlit_elements/frontend/build/_next/static/chunks/1400-46abb97c71e783b1.js
streamlit_elements/frontend/build/_next/static/chunks/1448.9d16e761885614bb.js
streamlit_elements/frontend/build/_next/static/chunks/1450.bf7b171d51da4e31.js
streamlit_elements/frontend/build/_next/static/chunks/1477.ab6e75f1296b5e50.js
streamlit_elements/frontend/build/_next/static/chunks/1521.0069d404171615f5.js
streamlit_elements/frontend/build/_next/static/chunks/1605.3bd1702c7ac1015f.js
streamlit_elements/frontend/build/_next/static/chunks/1609.b5ca0fb6032a0950.js
streamlit_elements_fte-0.1.3.dist-info/LICENSE
streamlit_elements_fte-0.1.3.dist-info/METADATA
streamlit_elements_fte-0.1.3.dist-info/WHEEL
streamlit_elements_fte-0.1.3.dist-info/top_level.txt
streamlit_elements_fte-0.1.3.dist-info/RECORD
