Metadata-Version: 2.1
Name: streamlit-elements-fte
Version: 0.1.3
Summary: React Components for Streamlit.
Home-page: https://share.streamlit.io/okld/streamlit-gallery/main?p=elements
Author: okld
License: MIT
Platform: UNKNOWN
Requires-Python: >= 3.6
Requires-Dist: streamlit>=1.4.0
